core/__init__.py
core/converter.py
core/meter.py
core/parser.py
core/torch_utils.py
core/utils.py
mnn_meter-1.0.0.dist-info/METADATA
mnn_meter-1.0.0.dist-info/WHEEL
mnn_meter-1.0.0.dist-info/top_level.txt
mnn_meter-1.0.0.dist-info/RECORD
