Metadata-Version: 2.1
Name: mnn-meter
Version: 1.0.0
Summary: Tools for quickly building operator latency tables and for accurately predicting model latency (based on Pytorch and MNN)
Author: Haolin Yan
Author-email: haolinyan_xdu@163.com
License: UNKNOWN
Project-URL: Source, https://github.com/makerlin1/MMT
Platform: UNKNOWN
Classifier: Development Status :: 4 - Beta
Classifier: Intended Audience :: Developers
Classifier: Topic :: Software Development :: Libraries
Classifier: Programming Language :: Python :: 3
Requires-Python: >=3.5
Requires-Dist: tabulate
Requires-Dist: pyyaml
